toolpy/__init__.py
toolpy/integrations/__init__.py
toolpy/integrations/groq/__init__.py
toolpy/integrations/groq/groq.py
toolpy/integrations/openai/__init__.py
toolpy/integrations/openai/openai.py
toolpy/llm/__init__.py
toolpy/llm/interface.py
toolpy/llm/registry.py
toolpy/tool/__init__.py
toolpy/tool/adapter.py
toolpy/tool/basic_tool.py
toolpy/tool/basic_wrappers.py
toolpy/tool/pipeline.py
toolpy/tool/router.py
toolpy/tool/tool.py
toolpy/tool/wrapper.py
llm_toolpy-0.3.2.dist-info/LICENSE
llm_toolpy-0.3.2.dist-info/METADATA
llm_toolpy-0.3.2.dist-info/WHEEL
llm_toolpy-0.3.2.dist-info/top_level.txt
llm_toolpy-0.3.2.dist-info/RECORD
