Metadata-Version: 2.2
Name: llm-toolpy
Version: 0.3.2
Summary: ToolPy is a Python module made to facilitate the creation of tools using LLMs.
Author-email: EltonCN <elton.nascimento@students.ic.unicamp.br>
Project-URL: Homepage, https://github.com/EltonCN/toolpy
Project-URL: Bug Tracker, https://github.com/EltonCN/toolpy/issues
Classifier: License :: OSI Approved :: MIT License
Classifier: Programming Language :: Python :: 3
Classifier: Operating System :: OS Independent
Classifier: Topic :: Scientific/Engineering
Classifier: Topic :: Scientific/Engineering :: Artificial Intelligence
Classifier: Intended Audience :: Science/Research
License-File: LICENSE
